chaosk6/__init__.py
chaosk6/actions.py
chaosk6/probes.py
chaosk6/scripts/probe.js
chaosk6/scripts/single-endpoint.js
chaostoolkit_k6-0.3.4.dist-info/LICENSE
chaostoolkit_k6-0.3.4.dist-info/METADATA
chaostoolkit_k6-0.3.4.dist-info/WHEEL
chaostoolkit_k6-0.3.4.dist-info/top_level.txt
chaostoolkit_k6-0.3.4.dist-info/RECORD
